response_report/__init__.py
response_report/reporter.py
response_report-1.1.1.dist-info/LICENSE
response_report-1.1.1.dist-info/METADATA
response_report-1.1.1.dist-info/WHEEL
response_report-1.1.1.dist-info/top_level.txt
response_report-1.1.1.dist-info/RECORD
