Metadata-Version: 2.1
Name: response-report
Version: 1.1.1
Summary: Save the response from the server. This may be needed when debugging.
Home-page: https://gitlab.com/whiteapfel/response_report
Author: WhiteApfel
Author-email: white@pfel.ru
License: Mozilla Public License 2.0
Project-URL: Donate, https://pfel.cc/donate
Project-URL: Telegram, https://t.me/apfel
Platform: UNKNOWN
License-File: LICENSE
